denku/__init__.py
denku/image/__init__.py
denku/memory/__init__.py
denku/utils/__init__.py
denku/video/__init__.py
denku/visualization/__init__.py
denku-0.1.5.dist-info/licenses/LICENSE
denku-0.1.5.dist-info/METADATA
denku-0.1.5.dist-info/WHEEL
denku-0.1.5.dist-info/top_level.txt
denku-0.1.5.dist-info/RECORD
