Metadata-Version: 2.4
Name: denku
Version: 0.1.5
Summary: Custom computer vision utilities for image and video processing, visualization, and memory management.
Author-email: Karachev Denis <welcomedenk@gmail.com>
License: Apache
Project-URL: homepage, https://github.com/TheDenk/denku
Project-URL: bug-tracker, https://github.com/TheDenk/denku/issues
Keywords: computer-vision,image-processing,video-processing,visualization,opencv,numpy,pytorch
Classifier: Development Status :: 4 - Beta
Classifier: Intended Audience :: Developers
Classifier: Intended Audience :: Science/Research
Classifier: License :: OSI Approved :: Apache Software License
Classifier: Programming Language :: Python :: 3
Classifier: Programming Language :: Python :: 3.8
Classifier: Programming Language :: Python :: 3.9
Classifier: Programming Language :: Python :: 3.10
Classifier: Topic :: Scientific/Engineering :: Image Processing
Requires-Python: >=3.8
License-File: LICENSE
Requires-Dist: numpy>=1.21.0
Requires-Dist: Pillow>=9.0.0
Requires-Dist: matplotlib>=3.5.0
Requires-Dist: opencv-python>=4.5.0
Requires-Dist: opencv-python-headless>=4.5.0
Requires-Dist: opencv-contrib-python>=4.5.0
Requires-Dist: tqdm>=4.65.0
Requires-Dist: requests>=2.28.0
Provides-Extra: dev
Requires-Dist: pytest<8.0.0,>=7.0.0; extra == "dev"
Requires-Dist: pytest-cov<5.0.0,>=4.0.0; extra == "dev"
Requires-Dist: pytest-mock<4.0.0,>=3.10.0; extra == "dev"
Requires-Dist: pre-commit<4.0.0,>=3.0.0; extra == "dev"
Requires-Dist: black<24.0.0,>=23.0.0; extra == "dev"
Requires-Dist: isort<6.0.0,>=5.12.0; extra == "dev"
Requires-Dist: flake8<7.0.0,>=6.0.0; extra == "dev"
Requires-Dist: mypy<2.0.0,>=1.0.0; extra == "dev"
Dynamic: license-file
